firestoredb/__init__.py
firestoredb-0.1.0.dist-info/LICENSE
firestoredb-0.1.0.dist-info/METADATA
firestoredb-0.1.0.dist-info/WHEEL
firestoredb-0.1.0.dist-info/top_level.txt
firestoredb-0.1.0.dist-info/RECORD
